dwollaswagger/__init__.py
dwollaswagger/api_client.py
dwollaswagger/configuration.py
dwollaswagger/rest.py
dwollaswagger/apis/__init__.py
dwollaswagger/apis/accounts_api.py
dwollaswagger/apis/businessclassifications_api.py
dwollaswagger/apis/customers_api.py
dwollaswagger/apis/documents_api.py
dwollaswagger/apis/events_api.py
dwollaswagger/apis/fundingsources_api.py
dwollaswagger/apis/masspaymentitems_api.py
dwollaswagger/apis/masspayments_api.py
dwollaswagger/apis/ondemandauthorizations_api.py
dwollaswagger/apis/root_api.py
dwollaswagger/apis/transfers_api.py
dwollaswagger/apis/webhooks_api.py
dwollaswagger/apis/webhooksubscriptions_api.py
dwollaswagger/models/__init__.py
dwollaswagger/models/account_info.py
dwollaswagger/models/account_o_auth_token.py
dwollaswagger/models/amount.py
dwollaswagger/models/application_event.py
dwollaswagger/models/authorization.py
dwollaswagger/models/business_classification.py
dwollaswagger/models/business_classification_list_response.py
dwollaswagger/models/catalog_response.py
dwollaswagger/models/create_customer.py
dwollaswagger/models/create_funding_source_request.py
dwollaswagger/models/create_webhook.py
dwollaswagger/models/customer.py
dwollaswagger/models/customer_list_response.py
dwollaswagger/models/customer_o_auth_token.py
dwollaswagger/models/document.py
dwollaswagger/models/document_list_response.py
dwollaswagger/models/event_list_response.py
dwollaswagger/models/facilitator_fee_request.py
dwollaswagger/models/funding_source.py
dwollaswagger/models/funding_source_list_response.py
dwollaswagger/models/hal_link.py
dwollaswagger/models/iav_token.py
dwollaswagger/models/id.py
dwollaswagger/models/mass_payment.py
dwollaswagger/models/mass_payment_item.py
dwollaswagger/models/mass_payment_item_list_response.py
dwollaswagger/models/mass_payment_item_request_body.py
dwollaswagger/models/mass_payment_list_response.py
dwollaswagger/models/mass_payment_request_body.py
dwollaswagger-1.0.9.dist-info/DESCRIPTION.rst
dwollaswagger-1.0.9.dist-info/METADATA
dwollaswagger-1.0.9.dist-info/metadata.json
dwollaswagger-1.0.9.dist-info/RECORD
dwollaswagger-1.0.9.dist-info/top_level.txt
dwollaswagger-1.0.9.dist-info/WHEEL
