Metadata-Version: 2.0
Name: dwollaswagger
Version: 1.0.9
Summary: Dwolla API V2 client
Home-page: https://developers.dwolla.com
Author: Swagger Contributors, David Stancu
Author-email: david@dwolla.com
License: UNKNOWN
Keywords: Swagger,Dwolla API
Platform: UNKNOWN
Requires-Dist: urllib3 (>=1.10)
Requires-Dist: six (>=1.9)
Requires-Dist: certifi
